orchestrator/__init__.py
orchestrator/agentic_app.py
orchestrator/app.py
orchestrator/exception_handlers.py
orchestrator/llm_settings.py
orchestrator/log_config.py
orchestrator/py.typed
orchestrator/security.py
orchestrator/settings.py
orchestrator/targets.py
orchestrator/types.py
orchestrator/version.py
orchestrator/workflow.py
orchestrator/api/__init__.py
orchestrator/api/error_handling.py
orchestrator/api/helpers.py
orchestrator/api/models.py
orchestrator/api/api_v1/__init__.py
orchestrator/api/api_v1/api.py
orchestrator/api/api_v1/endpoints/__init__.py
orchestrator/api/api_v1/endpoints/agent.py
orchestrator/api/api_v1/endpoints/health.py
orchestrator/api/api_v1/endpoints/processes.py
orchestrator/api/api_v1/endpoints/product_blocks.py
orchestrator/api/api_v1/endpoints/products.py
orchestrator/api/api_v1/endpoints/resource_types.py
orchestrator/api/api_v1/endpoints/schedules.py
orchestrator/api/api_v1/endpoints/search.py
orchestrator/api/api_v1/endpoints/settings.py
orchestrator/api/api_v1/endpoints/subscription_customer_descriptions.py
orchestrator/api/api_v1/endpoints/subscriptions.py
orchestrator/api/api_v1/endpoints/translations.py
orchestrator/api/api_v1/endpoints/user.py
orchestrator/api/api_v1/endpoints/workflows.py
orchestrator/api/api_v1/endpoints/ws.py
orchestrator/cli/__init__.py
orchestrator/cli/database.py
orchestrator/cli/generate.py
orchestrator/cli/main.py
orchestrator/cli/migrate_domain_models.py
orchestrator/cli/migrate_tasks.py
orchestrator/cli/migrate_workflows.py
orchestrator/cli/migration_helpers.py
orchestrator/cli/scheduler.py
orchestrator/cli/domain_gen_helpers/__init__.py
orchestrator/cli/domain_gen_helpers/fixed_input_helpers.py
orchestrator/cli/domain_gen_helpers/helpers.py
orchestrator/cli/domain_gen_helpers/product_block_helpers.py
orchestrator/cli/domain_gen_helpers/product_helpers.py
orchestrator/cli/domain_gen_helpers/resource_type_helpers.py
orchestrator/cli/domain_gen_helpers/types.py
orchestrator/cli/generator/__init__.py
orchestrator_core-4.7.1.dist-info/licenses/LICENSE
orchestrator_core-4.7.1.dist-info/WHEEL
orchestrator_core-4.7.1.dist-info/METADATA
orchestrator_core-4.7.1.dist-info/RECORD
