Metadata-Version: 2.4
Name: orchestrator-core
Version: 4.7.1
Summary: This is the orchestrator workflow engine.
Author-email: SURF <automation-beheer@surf.nl>
Requires-Python: >=3.11,<3.15
License-Expression: Apache-2.0
Classifier: Development Status :: 5 - Production/Stable
Classifier: Environment :: Web Environment
Classifier: Framework :: AsyncIO
Classifier: Framework :: FastAPI
Classifier: Intended Audience :: Developers
Classifier: Intended Audience :: Information Technology
Classifier: Intended Audience :: System Administrators
Classifier: Intended Audience :: Telecommunications Industry
Classifier: Operating System :: OS Independent
Classifier: Programming Language :: Python :: 3 :: Only
Classifier: Programming Language :: Python :: 3
Classifier: Programming Language :: Python :: 3.11
Classifier: Programming Language :: Python :: 3.12
Classifier: Programming Language :: Python :: 3.13
Classifier: Programming Language :: Python :: 3.14
Classifier: Programming Language :: Python
Classifier: Topic :: Internet :: WWW/HTTP :: HTTP Servers
Classifier: Topic :: Internet :: WWW/HTTP
Classifier: Topic :: Internet
Classifier: Topic :: Software Development :: Libraries :: Application Frameworks
Classifier: Topic :: Software Development :: Libraries :: Python Modules
Classifier: Topic :: Software Development :: Libraries
Classifier: Topic :: Software Development
Classifier: Typing :: Typed
License-File: LICENSE
Requires-Dist: alembic==1.18.1
Requires-Dist: anyio>=3.7.0
Requires-Dist: apscheduler>=3.11.0
Requires-Dist: click==8.*
Requires-Dist: deepmerge==2.0
Requires-Dist: deprecated>=1.2.18
Requires-Dist: fastapi~=0.128.0
Requires-Dist: fastapi-etag==0.4.0
Requires-Dist: itsdangerous>=2.2.0
Requires-Dist: jinja2==3.1.6
Requires-Dist: more-itertools~=10.8.0
Requires-Dist: nwa-stdlib~=1.11.0
Requires-Dist: oauth2-lib>=2.5.0
Requires-Dist: orjson==3.11.5
Requires-Dist: pgvector>=0.4.1
Requires-Dist: prometheus-client==0.24.1
Requires-Dist: psycopg2-binary==2.9.11
Requires-Dist: pydantic-forms>=1.4.0
Requires-Dist: pydantic-settings~=2.12.0
Requires-Dist: pydantic[email]~=2.12.4
Requires-Dist: python-dateutil==2.9.0.post0
Requires-Dist: python-rapidjson>=1.23,<1.24
Requires-Dist: pytz==2025.2
Requires-Dist: redis==7.1.0
Requires-Dist: semver==3.0.4
Requires-Dist: sentry-sdk[fastapi]>=2.29.1
Requires-Dist: sqlalchemy==2.0.45
Requires-Dist: sqlalchemy-utils==0.42.1
Requires-Dist: strawberry-graphql>=0.281.0,<0.285.0
Requires-Dist: structlog>=25.4.0
Requires-Dist: tabulate==0.9.0
Requires-Dist: typer==0.21.1
Requires-Dist: uvicorn[standard]~=0.40.0
Requires-Dist: pydantic-ai-slim >=1.27.0 ; extra == "agent"
Requires-Dist: ag-ui-protocol>=0.1.10 ; extra == "agent"
Requires-Dist: litellm>=1.75.7 ; extra == "agent"
Requires-Dist: celery~=5.6.0 ; extra == "celery"
Requires-Dist: litellm>=1.80.0 ; extra == "search"
Project-URL: Documentation, https://workfloworchestrator.org/orchestrator-core
Project-URL: Homepage, https://workfloworchestrator.org/orchestrator-core
Project-URL: Source, https://github.com/workfloworchestrator/orchestrator-core
Provides-Extra: agent
Provides-Extra: celery
Provides-Extra: search
